[
  {
    "id": "num_001",
    "type": "number",
    "difficulty": "medium",
    "category": "sciences",
    "label": "À quelle température (en °C) l'eau bout-elle au niveau de la mer ?",
    "answer": "100",
    "acceptedAnswers": ["100"],
    "media": null,
    "explanation": "L'eau bout à 100°C sous pression atmosphérique standard.",
    "tags": ["sciences", "physique"],
    "baseTimer": 20,
    "tolerance": 0
  },
  {
    "id": "num_002",
    "type": "number",
    "difficulty": "medium",
    "category": "géographie",
    "label": "Combien de pays compte l'Union européenne (2024) ?",
    "answer": "27",
    "acceptedAnswers": ["27"],
    "media": null,
    "explanation": "L'UE compte 27 États membres depuis le Brexit en 2020.",
    "tags": ["géographie", "politique"],
    "baseTimer": 25,
    "tolerance": 0
  },
  {
    "id": "num_003",
    "type": "number",
    "difficulty": "hard",
    "category": "histoire",
    "label": "En quelle année a débuté la Première Guerre mondiale ?",
    "answer": "1914",
    "acceptedAnswers": ["1914"],
    "media": null,
    "explanation": "La Première Guerre mondiale débute le 28 juillet 1914.",
    "tags": ["histoire"],
    "baseTimer": 25,
    "tolerance": 0
  },
  {
    "id": "num_004",
    "type": "number",
    "difficulty": "easy",
    "category": "sciences",
    "label": "Combien de continents y a-t-il sur Terre ?",
    "answer": "7",
    "acceptedAnswers": ["7"],
    "media": null,
    "explanation": "Les 7 continents : Afrique, Antarctique, Asie, Europe, Amérique du Nord, Amérique du Sud, Océanie.",
    "tags": ["sciences", "géographie"],
    "baseTimer": 15,
    "tolerance": 0
  },
  {
    "id": "num_005",
    "type": "number",
    "difficulty": "hard",
    "category": "sciences",
    "label": "Quelle est la vitesse de la lumière en km/s (arrondie) ?",
    "answer": "300000",
    "acceptedAnswers": ["300000", "299792"],
    "media": null,
    "explanation": "La vitesse de la lumière est d'environ 299 792 km/s.",
    "tags": ["sciences", "physique"],
    "baseTimer": 30,
    "tolerance": 1000
  },
  {
    "id": "num_006",
    "type": "number",
    "difficulty": "medium",
    "category": "géographie",
    "label": "Combien de départements y a-t-il en France métropolitaine ?",
    "answer": "96",
    "acceptedAnswers": ["96"],
    "media": null,
    "explanation": "La France métropolitaine compte 96 départements.",
    "tags": ["géographie", "france"],
    "baseTimer": 25,
    "tolerance": 1
  },
  {
    "id": "num_007",
    "type": "number",
    "difficulty": "easy",
    "category": "sciences",
    "label": "Combien de chromosomes possède un être humain ?",
    "answer": "46",
    "acceptedAnswers": ["46"],
    "media": null,
    "explanation": "23 paires de chromosomes.",
    "tags": ["sciences", "biologie"],
    "baseTimer": 20,
    "tolerance": 0
  },
  {
    "id": "num_008",
    "type": "number",
    "difficulty": "hard",
    "category": "géographie",
    "label": "Quelle est la population mondiale approximative en milliards (2024) ?",
    "answer": "8",
    "acceptedAnswers": ["8"],
    "media": null,
    "explanation": "La population mondiale a franchi les 8 milliards en novembre 2022.",
    "tags": ["géographie", "démographie"],
    "baseTimer": 20,
    "tolerance": 0.5
  },
  {
    "id": "num_009",
    "type": "number",
    "difficulty": "medium",
    "category": "sport",
    "label": "Combien de kilomètres fait un marathon ?",
    "answer": "42",
    "acceptedAnswers": ["42", "42.195"],
    "media": null,
    "explanation": "La distance exacte est de 42,195 km.",
    "tags": ["sport", "athlétisme"],
    "baseTimer": 20,
    "tolerance": 1
  },
  {
    "id": "num_010",
    "type": "number",
    "difficulty": "easy",
    "category": "culture",
    "label": "Combien de notes composent une gamme musicale classique ?",
    "answer": "7",
    "acceptedAnswers": ["7"],
    "media": null,
    "explanation": "Do, Ré, Mi, Fa, Sol, La, Si.",
    "tags": ["culture", "musique"],
    "baseTimer": 15,
    "tolerance": 0
  },
  {
    "id": "num_011",
    "type": "number",
    "difficulty": "hard",
    "category": "géographie",
    "label": "Quelle est la hauteur du Mont Blanc en mètres ?",
    "answer": "4808",
    "acceptedAnswers": ["4808", "4807"],
    "media": null,
    "explanation": "Le Mont Blanc culmine à 4 808 m.",
    "tags": ["géographie", "montagnes"],
    "baseTimer": 30,
    "tolerance": 5
  },
  {
    "id": "num_012",
    "type": "number",
    "difficulty": "medium",
    "category": "histoire",
    "label": "En quelle année Christophe Colomb a-t-il découvert l'Amérique ?",
    "answer": "1492",
    "acceptedAnswers": ["1492"],
    "media": null,
    "explanation": "Colomb est arrivé aux Amériques le 12 octobre 1492.",
    "tags": ["histoire", "explorations"],
    "baseTimer": 20,
    "tolerance": 0
  },
  {
    "id": "num_013",
    "type": "number",
    "difficulty": "easy",
    "category": "sciences",
    "label": "Combien de dents possède un adulte ?",
    "answer": "32",
    "acceptedAnswers": ["32"],
    "media": null,
    "explanation": "Un adulte possède normalement 32 dents, dont 4 dents de sagesse.",
    "tags": ["sciences", "biologie"],
    "baseTimer": 20,
    "tolerance": 0
  },
  {
    "id": "num_014",
    "type": "number",
    "difficulty": "hard",
    "category": "technologie",
    "label": "En quelle année Internet a-t-il été inventé (ARPANET) ?",
    "answer": "1969",
    "acceptedAnswers": ["1969"],
    "media": null,
    "explanation": "Le premier message ARPANET a été envoyé le 29 octobre 1969.",
    "tags": ["technologie", "internet"],
    "baseTimer": 30,
    "tolerance": 0
  },
  {
    "id": "num_015",
    "type": "number",
    "difficulty": "medium",
    "category": "sport",
    "label": "Combien de trous comporte un parcours de golf standard ?",
    "answer": "18",
    "acceptedAnswers": ["18"],
    "media": null,
    "explanation": "Un parcours de golf standard comporte 18 trous.",
    "tags": ["sport", "golf"],
    "baseTimer": 20,
    "tolerance": 0
  },
  {
    "id": "num_016",
    "type": "number",
    "difficulty": "easy",
    "category": "nature",
    "label": "Combien de pattes a un insecte ?",
    "answer": "6",
    "acceptedAnswers": ["6"],
    "media": null,
    "explanation": "Tous les insectes possèdent exactement 6 pattes.",
    "tags": ["nature", "insectes"],
    "baseTimer": 15,
    "tolerance": 0
  },
  {
    "id": "num_017",
    "type": "number",
    "difficulty": "hard",
    "category": "sciences",
    "label": "En quelle année l'Homme a-t-il marché sur la Lune pour la première fois ?",
    "answer": "1969",
    "acceptedAnswers": ["1969"],
    "media": null,
    "explanation": "Neil Armstrong a posé le pied sur la Lune le 20 juillet 1969.",
    "tags": ["sciences", "espace"],
    "baseTimer": 25,
    "tolerance": 0
  },
  {
    "id": "num_018",
    "type": "number",
    "difficulty": "medium",
    "category": "culture",
    "label": "Combien de touches possède un piano standard ?",
    "answer": "88",
    "acceptedAnswers": ["88"],
    "media": null,
    "explanation": "Un piano standard possède 88 touches (52 blanches et 36 noires).",
    "tags": ["culture", "musique", "instruments"],
    "baseTimer": 25,
    "tolerance": 0
  },
  {
    "id": "num_019",
    "type": "number",
    "difficulty": "easy",
    "category": "sport",
    "label": "Combien de joueurs composent une équipe de rugby à XV ?",
    "answer": "15",
    "acceptedAnswers": ["15"],
    "media": null,
    "explanation": "Le rugby à XV oppose deux équipes de 15 joueurs.",
    "tags": ["sport", "rugby"],
    "baseTimer": 15,
    "tolerance": 0
  },
  {
    "id": "num_020",
    "type": "number",
    "difficulty": "hard",
    "category": "géographie",
    "label": "Quelle est la profondeur de la fosse des Mariannes en mètres ?",
    "answer": "11034",
    "acceptedAnswers": ["11034", "11000", "10994"],
    "media": null,
    "explanation": "La fosse des Mariannes est le point le plus profond des océans.",
    "tags": ["géographie", "océans", "records"],
    "baseTimer": 30,
    "tolerance": 100
  },
  {
    "id": "num_021",
    "type": "number",
    "difficulty": "medium",
    "category": "nature",
    "label": "Combien d'espèces de pingouins existent environ ?",
    "answer": "18",
    "acceptedAnswers": ["18", "17", "19"],
    "media": null,
    "explanation": "On recense entre 17 et 19 espèces de manchots.",
    "tags": ["nature", "animaux"],
    "baseTimer": 25,
    "tolerance": 2
  },
  {
    "id": "num_022",
    "type": "number",
    "difficulty": "easy",
    "category": "gastronomie",
    "label": "Combien de points cardinaux existe-t-il ?",
    "answer": "4",
    "acceptedAnswers": ["4"],
    "media": null,
    "explanation": "Nord, Sud, Est, Ouest.",
    "tags": ["culture", "géographie"],
    "baseTimer": 15,
    "tolerance": 0
  },
  {
    "id": "num_023",
    "type": "number",
    "difficulty": "hard",
    "category": "technologie",
    "label": "En quelle année a été fondé Google ?",
    "answer": "1998",
    "acceptedAnswers": ["1998"],
    "media": null,
    "explanation": "Google a été fondé par Larry Page et Sergey Brin en 1998.",
    "tags": ["technologie", "internet"],
    "baseTimer": 25,
    "tolerance": 0
  },
  {
    "id": "num_024",
    "type": "number",
    "difficulty": "medium",
    "category": "cinéma",
    "label": "Combien de films composent la saga 'Star Wars' principale (épisodes) ?",
    "answer": "9",
    "acceptedAnswers": ["9"],
    "media": null,
    "explanation": "La saga Skywalker compte 9 épisodes principaux.",
    "tags": ["cinéma", "science-fiction"],
    "baseTimer": 20,
    "tolerance": 0
  },
  {
    "id": "num_025",
    "type": "number",
    "difficulty": "easy",
    "category": "musique",
    "label": "Combien de cordes possède un ukulélé ?",
    "answer": "4",
    "acceptedAnswers": ["4"],
    "media": null,
    "explanation": "Le ukulélé standard possède 4 cordes.",
    "tags": ["musique", "instruments"],
    "baseTimer": 15,
    "tolerance": 0
  }
]
